reverse_geocode_bd/__init__.py
reverse_geocode_bd/small_bangladesh_geojson_adm4_5160_unions_thanas.json
reverse_geocode_bd-1.0.7.dist-info/LICENSE
reverse_geocode_bd-1.0.7.dist-info/METADATA
reverse_geocode_bd-1.0.7.dist-info/WHEEL
reverse_geocode_bd-1.0.7.dist-info/top_level.txt
reverse_geocode_bd-1.0.7.dist-info/RECORD
