Metadata-Version: 2.1
Name: reverse-geocode-bd
Version: 1.0.7
Summary: Offline reverse geocoder for Bangladesh Map
Home-page: https://github.com/ShakhrulSiam268/reverse_geocode_bd
Author: Shakhrul Iman Siam
Author-email: shakhrulsiam268@gmail.com
Classifier: Programming Language :: Python :: 3
Classifier: License :: OSI Approved :: MIT License
Classifier: Operating System :: OS Independent
License-File: LICENSE
